email/manifest.toml
email/smtp.py
opsbox_email_output-0.1.5.dist-info/LICENCE.txt
opsbox_email_output-0.1.5.dist-info/METADATA
opsbox_email_output-0.1.5.dist-info/WHEEL
opsbox_email_output-0.1.5.dist-info/entry_points.txt
opsbox_email_output-0.1.5.dist-info/top_level.txt
opsbox_email_output-0.1.5.dist-info/RECORD
