Metadata-Version: 2.2
Name: opsbox-email-output
Version: 0.1.5
Summary: Email output for Opsbox
License: Mozilla Public License Version 2.0
Requires-Python: ==3.11.*
License-File: LICENCE.txt
Requires-Dist: loguru>=0.7.2
Requires-Dist: pluggy>=1.5.0
Requires-Dist: pydantic>=2.10.2
Requires-Dist: opsbox-general-handler>=0.1.2
